siyuanyuque/__init__.py
siyuanyuque/__main__.py
siyuanyuque/config.py
siyuanyuque/yuque.py
siyuanyuque-0.1.1.dist-info/entry_points.txt
siyuanyuque-0.1.1.dist-info/LICENSE
siyuanyuque-0.1.1.dist-info/WHEEL
siyuanyuque-0.1.1.dist-info/METADATA
siyuanyuque-0.1.1.dist-info/RECORD
