Metadata-Version: 2.1
Name: siyuanyuque
Version: 0.1.1
Summary: Sync SiYuan with Yuque
Home-page: https://www.github.com/Clouder0/siyuanyuque
License: MIT
Author: clouder
Author-email: clouder0@outlook.com
Requires-Python: >=3.9,<4.0
Classifier: Development Status :: 2 - Pre-Alpha
Classifier: Framework :: Flake8
Classifier: Framework :: Pytest
Classifier: Framework :: tox
Classifier: License :: OSI Approved :: MIT License
Classifier: Natural Language :: English
Classifier: Operating System :: OS Independent
Classifier: Programming Language :: Python :: 3
Classifier: Programming Language :: Python :: 3.10
Classifier: Programming Language :: Python :: 3.9
Classifier: Topic :: Utilities
Classifier: Typing :: Typed
Requires-Dist: dynaconf (>=3.1.8,<4.0.0)
Requires-Dist: httpx (>=0.22.0,<0.23.0)
Requires-Dist: siyuanhelper (>=0.2.0,<0.3.0)
Project-URL: Repository, https://www.github.com/Clouder0/siyuanyuque
